Workbook

Sheet Test Cases
A1: ID | B1: Module | C1: Title | D1: Priority | E1: Type | F1: Preconditions | G1: Steps | H1: Test data | I1: Expected result | J1: Automation status | K1: Automated test
A2: TC_REG_01 | B2: Register | C2: Register with valid data | D2: High | E2: Positive | F2: The home page is open; no customer is logged in | G2: 1. Click Register in the header 2. Select a gender and fill in First name, Last name, Email, Password, Confirm password 3. Click Register | H2: Unique email (generated), password Test@12345 | I2: Message 'Your registration completed' is displayed. The customer is logged in: the email is displayed in the header. | J2: Automated | K2: RegisterTest.registerWithValidData
A3: TC_REG_02 | B3: Register | C3: Register with all mandatory fields empty | D3: Medium | E3: Negative | F3: The home page is open; no customer is logged in | G3: 1. Click Register in the header 2. Leave all fields empty 3. Click Register | H3: - | I3: The account is not created. Messages displayed: 'First name is required.', 'Last name is required.', 'Email is required.', 'Password is required.' (for both password fields). | J3: Automated | K3: RegisterTest.registerWithEmptyMandatoryFields
A4: TC_REG_03 | B4: Register | C4: Register with an invalid email format | D4: Medium | E4: Negative | F4: The home page is open; no customer is logged in | G4: 1. Click Register in the header 2. Fill in the form with an email without '@' 3. Click Register | H4: Email: ana.tester.example.com | I4: The account is not created. Message 'Wrong email' is displayed next to the Email field. | J4: Automated | K4: RegisterTest.registerWithInvalidEmailFormat
A5: TC_REG_04 | B5: Register | C5: Register with a password shorter than 6 characters | D5: Medium | E5: Negative | F5: The home page is open; no customer is logged in | G5: 1. Click Register in the header 2. Fill in the form with a 5 character password in both password fields 3. Click Register | H5: Password: 12345 | I5: The account is not created. Message 'The password should have at least 6 characters.' is displayed. | J5: Automated | K5: RegisterTest.registerWithShortPassword
A6: TC_REG_05 | B6: Register | C6: Register with a different confirmation password | D6: Medium | E6: Negative | F6: The home page is open; no customer is logged in | G6: 1. Click Register in the header 2. Fill in the form with different values in Password and Confirm password 3. Click Register | H6: Test@12345 / Test@54321 | I6: The account is not created. Message 'The password and confirmation password do not match.' is displayed. | J6: Automated | K6: RegisterTest.registerWithMismatchedPasswords
A7: TC_REG_06 | B7: Register | C7: Register with an email that is already registered | D7: High | E7: Negative | F7: An account with the email already exists; no customer is logged in | G7: 1. Click Register in the header 2. Fill in the form with the email of the existing account 3. Click Register | H7: Email of the existing account | I7: The account is not created. Message 'The specified email already exists' is displayed. | J7: Automated | K7: RegisterTest.registerWithExistingEmail
A8: TC_LOG_01 | B8: Login | C8: Login with valid credentials | D8: High | E8: Positive | F8: A registered account exists; no customer is logged in | G8: 1. Click Log in in the header 2. Enter the email and the password of the account 3. Click Log in | H8: Email and password of the account | I8: The customer is logged in: the email and the Log out link are displayed in the header. | J8: Automated | K8: LoginTest.loginWithValidCredentials
A9: TC_LOG_02 | B9: Login | C9: Login with a wrong password | D9: High | E9: Negative | F9: A registered account exists; no customer is logged in | G9: 1. Click Log in in the header 2. Enter the email of the account and a wrong password 3. Click Log in | H9: Password: WrongPass@999 | I9: The customer is not logged in. Message 'Login was unsuccessful. Please correct the errors and try again. The credentials provided are incorrect' is displayed. | J9: Automated | K9: LoginTest.loginWithWrongPassword
A10: TC_LOG_03 | B10: Login | C10: Login with an email that is not registered | D10: Medium | E10: Negative | F10: The home page is open; no customer is logged in | G10: 1. Click Log in in the header 2. Enter an email that has no account and any password 3. Click Log in | H10: Unique email (generated) | I10: The customer is not logged in. Message 'Login was unsuccessful. Please correct the errors and try again. No customer account found' is displayed. | J10: Automated | K10: LoginTest.loginWithUnregisteredEmail
A11: TC_LOG_04 | B11: Login | C11: Logout | D11: High | E11: Positive | F11: A customer is logged in | G11: 1. Click Log out in the header | H11: - | I11: The customer is logged out: the Log in link is displayed in the header and the Log out link is not. | J11: Automated | K11: LoginTest.logout
A12: TC_SRC_01 | B12: Search | C12: Search by an existing keyword | D12: High | E12: Positive | F12: The home page is open; no customer is logged in | G12: 1. Type the keyword in the search box from the header 2. Click Search | H12: Keyword: computer | I12: The Search page is displayed. At least one product is listed and every product title contains the keyword (not case sensitive). | J12: Automated | K12: SearchTest.searchByExistingKeyword
... A38: TC_CHK_06 | B38: Checkout | C38: Cart is emptied after the order is placed | D38: Medium | E38: Positive | F38: An order has just been placed | G38: 1. Open Shopping cart from the header | H38: - | I38: Message 'Your Shopping Cart is empty!' is displayed. | J38: Automated | K38: CheckoutTest.cartIsEmptyAfterOrder

Sheet Summary
A1: Demo Web Shop - Test case summary
A2: Application under test: https://demowebshop.tricentis.com/
A4: Module | B4: Total | C4: Automated | D4: Planned | E4: High priority
A5: Register | B5: =COUNTIF('Test Cases'!$B$2:$B$500,A5) -> 6 | C5: =COUNTIFS('Test Cases'!$B$2:$B$500,A5,'Test Cases'!$J$2:$J$500,"Automated") -> 6 | D5: =COUNTIFS('Test Cases'!$B$2:$B$500,A5,'Test Cases'!$J$2:$J$500,"Planned*") -> 0 | E5: =COUNTIFS('Test Cases'!$B$2:$B$500,A5,'Test Cases'!$D$2:$D$500,"High") -> 2
A6: Login | B6: =COUNTIF('Test Cases'!$B$2:$B$500,A6) -> 4 | C6: =COUNTIFS('Test Cases'!$B$2:$B$500,A6,'Test Cases'!$J$2:$J$500,"Automated") -> 4 | D6: =COUNTIFS('Test Cases'!$B$2:$B$500,A6,'Test Cases'!$J$2:$J$500,"Planned*") -> 0 | E6: =COUNTIFS('Test Cases'!$B$2:$B$500,A6,'Test Cases'!$D$2:$D$500,"High") -> 3
A7: Search | B7: =COUNTIF('Test Cases'!$B$2:$B$500,A7) -> 5 | C7: =COUNTIFS('Test Cases'!$B$2:$B$500,A7,'Test Cases'!$J$2:$J$500,"Automated") -> 5 | D7: =COUNTIFS('Test Cases'!$B$2:$B$500,A7,'Test Cases'!$J$2:$J$500,"Planned*") -> 0 | E7: =COUNTIFS('Test Cases'!$B$2:$B$500,A7,'Test Cases'!$D$2:$D$500,"High") -> 1
A8: Catalogue | B8: =COUNTIF('Test Cases'!$B$2:$B$500,A8) -> 7 | C8: =COUNTIFS('Test Cases'!$B$2:$B$500,A8,'Test Cases'!$J$2:$J$500,"Automated") -> 7 | D8: =COUNTIFS('Test Cases'!$B$2:$B$500,A8,'Test Cases'!$J$2:$J$500,"Planned*") -> 0 | E8: =COUNTIFS('Test Cases'!$B$2:$B$500,A8,'Test Cases'!$D$2:$D$500,"High") -> 2
A9: Cart | B9: =COUNTIF('Test Cases'!$B$2:$B$500,A9) -> 6 | C9: =COUNTIFS('Test Cases'!$B$2:$B$500,A9,'Test Cases'!$J$2:$J$500,"Automated") -> 6 | D9: =COUNTIFS('Test Cases'!$B$2:$B$500,A9,'Test Cases'!$J$2:$J$500,"Planned*") -> 0 | E9: =COUNTIFS('Test Cases'!$B$2:$B$500,A9,'Test Cases'!$D$2:$D$500,"High") -> 3
A10: Wishlist | B10: =COUNTIF('Test Cases'!$B$2:$B$500,A10) -> 3 | C10: =COUNTIFS('Test Cases'!$B$2:$B$500,A10,'Test Cases'!$J$2:$J$500,"Automated") -> 3 | D10: =COUNTIFS('Test Cases'!$B$2:$B$500,A10,'Test Cases'!$J$2:$J$500,"Planned*") -> 0 | E10: =COUNTIFS('Test Cases'!$B$2:$B$500,A10,'Test Cases'!$D$2:$D$500,"High") -> 0
A11: Checkout | B11: =COUNTIF('Test Cases'!$B$2:$B$500,A11) -> 6 | C11: =COUNTIFS('Test Cases'!$B$2:$B$500,A11,'Test Cases'!$J$2:$J$500,"Automated") -> 6 | D11: =COUNTIFS('Test Cases'!$B$2:$B$500,A11,'Test Cases'!$J$2:$J$500,"Planned*") -> 0 | E11: =COUNTIFS('Test Cases'!$B$2:$B$500,A11,'Test Cases'!$D$2:$D$500,"High") -> 4
A12: Total | B12: =SUM(B5:B11) -> 37 | C12: =SUM(C5:C11) -> 37 | D12: =SUM(D5:D11) -> 0 | E12: =SUM(E5:E11) -> 15
A14: Automation coverage | B14: =IF(B12=0,0,C12/B12) -> 1
A16: Notes
A17: Automation status is a drop-down on the Test Cases sheet; this summary recalculates from it.
A18: All 37 test cases are automated. README and GitHub Actions pipeline added.
A19: Expected results quoted in apostrophes are the exact texts of the application, read from the site on 2026-10-07.
A20: Runs on Chrome: 2026-10-07 Register and Login, 10 of 10 passed; 2026-10-08 up to Search and Catalogue, 22 of 22 passed; 2026-10-08 up to Cart and Wishlist, 31 of 31 passed. 2026-10-08 all modules: 35 of 37 passed; TC_CHK_04 and TC_CHK_05 failed on the timing of the checkout steps, fixed in CheckoutPage (to be confirmed by the next run).
